{
              "bi_grams": "[Business Development, Business Strategy, FrenchDavid Botbol, EVP Director, Business Development, Food Truck, Truck Promotions, United States, strong multicultural, multicultural background, multiple startups, startups Extremely, Extremely analytical, analytical creative, creative problem, problem solver, Food Truck, Truck Promotions, Executive VP, VP Director, Business Development, Food Truck, Truck Promotions, experiential marketing, marketing agency, Streets\u2122, custom branded, branded vehicles, oneofakind experiences, establishing meaningful, meaningful connections, Food Truck, Truck Association, Association Los, Los Angeles, Executive VP, VP Director, Business Development, Los Angeles, Angeles California, California United, United States, New York, York Food, Food Truck, Truck Association, Association NYFTA, Executive VP, VP Director, Business Development, Business Dev, Dev Manager, Tel Aviv, Aviv Area, Area Israel, Business Development, Tel Aviv, Aviv Area, Area Israel, Diaphanum LLC, Managing Partner, BHS Partners, Partners LP, Portfolio Manager, Brahman Capital, Research Analyst, IDC Herzliya, Global MBA, Business Strategy, Columbia University, New York, Exchange Program, Program MBA, Binghamton University]",
              "clean_data": "\u00a0 \u00a0\nContact\n\nLinkedIn\nTop Skills\nBusiness Development\nBusiness Strategy\nStartups\nLanguages\nEnglish\nFrenchDavid Botbol\nEVP Director of Business Development at Food Truck Promotions\nUnited States\nSummary\nEntrepreneur with strong multicultural background and experiences\nFounded several companies and assisted in the development of\nmultiple startups Extremely analytical creative problem solver and\nstrong in sales / marketing\nExperience\nFood Truck Promotions\nExecutive VP Director Of Business Development\nJune 2020\u00a0\u00a0Present\u00a0 3 years 5 months\nFood Truck Promotions is an experiential marketing agency that will Bring Your\nBrand to the Streets\u2122 with custom branded vehicles We focus on creating\noneofakind experiences and establishing meaningful connections between\nbrands and their consumers\nFood Truck Association Los Angeles\nExecutive VP Director of Business Development\nDecember 2021\u00a0\u00a0Present\u00a0 1 year 11 months\nLos Angeles California United States\nNew York Food Truck Association NYFTA\nExecutive VP Director of Business Development \n2018\u00a0\u00a0Present\u00a0 5 years\nHola\nBusiness Dev Manager\nNovember 2017\u00a0\u00a0June 2018\u00a0 8 months\nTel Aviv Area Israel\nWisor\nHead Of Business Development\nDecember 2016\u00a0\u00a0November 2017\u00a0 1 year\nTel Aviv Area Israel\n\u00a0 Page 1 of 2 \u00a0 \u00a0\nDiaphanum LLC\nManaging Partner\nJanuary 2016\u00a0\u00a0October 2016\u00a0 10 months\nBHS Partners LP\nFounder / Portfolio Manager\nJanuary 2015\u00a0\u00a0December 2015\u00a0 1 year\nBrahman Capital\nResearch Analyst\nJune 2013\u00a0\u00a0December 2014\u00a0 1 year 7 months\nEducation\nIDC Herzliya\nGlobal MBA\u00a0Business Strategy and Development \u00a0\u00a02016\u00a0\u00a02018\nColumbia University in the City of New York\nExchange Program MBA\u00a0 \u00a0\u00a02017\u00a0\u00a02017\nBinghamton University\nBachelor's degree\u00a0Economics \u00a0\u00a02009\u00a0\u00a02013\n\u00a0 Page 2 of 2",
              "emails": [],
              "entities": [
                            "Business Development",
                            "Streets",
                            "California",
                            "Food Truck Association",
                            "Binghamton University",
                            "Brahman Capital\nResearch Analyst",
                            "Economics",
                            "United States",
                            "Tel Aviv Area",
                            "the City of New York\nExchange",
                            "IDC Herzliya\nGlobal MBA\u00a0Business Strategy and Development",
                            "New York Food Truck Association",
                            "Los Angeles",
                            "EVP",
                            "Food Truck Promotions",
                            "Education",
                            "Business Development at Food Truck Promotions",
                            "NYFTA",
                            "Bachelor",
                            "Israel",
                            "Columbia University",
                            "BHS Partners LP\nFounder / Portfolio"
              ],
              "experience": "Skills \n Business Development \n Business Strategy \n Startups \n Languages \n English \n FrenchDavid Botbol \n EVP Director of Business Development at Food Truck Promotions \n United States \n Summary \n Entrepreneur with strong multicultural background and experiences \n Founded several companies and assisted in the development of \n multiple startups Extremely analytical creative problem solver and \n strong in sales / marketing \n Experience \n Food Truck Promotions \n Executive VP Director Of Business Development \n June 2020 \u00a0\u00a0 Present \u00a0  3 years 5 months \n Food Truck Promotions is an experiential marketing agency that will Bring Your \n Brand to the Streets \u2122 with custom branded vehicles We focus on creating \n oneofakind experiences and establishing meaningful connections between \n brands and their consumers \n Food Truck Association Los Angeles \n Executive VP Director of Business Development \n December 2021 \u00a0\u00a0 Present \u00a0  1 year 11 months \n Los Angeles California United States \n New York Food Truck Association NYFTA \n Executive VP Director of Business Development \n 2018 \u00a0\u00a0 Present \u00a0  5 years \n Hola \n Business Dev Manager \n November 2017 \u00a0\u00a0 June 2018 \u00a0  8 months \n Tel Aviv Area Israel \n Wisor \n Head Of Business Development \n December 2016 \u00a0\u00a0 November 2017 \u00a0  1 year \n Tel Aviv Area Israel \n\u00a0  Page 1 of 2 \u00a0 \u00a0\n Diaphanum LLC \n Managing Partner \n January 2016 \u00a0\u00a0 October 2016 \u00a0  10 months \n BHS Partners LP \n Founder / Portfolio Manager \n January 2015 \u00a0\u00a0 December 2015 \u00a0  1 year \n Brahman Capital \n Research Analyst \n June 2013 \u00a0\u00a0 December 2014 \u00a0  1 year 7 months \n Education \n IDC Herzliya \n Global MBA \u00a0 Business Strategy and Development \u00a0\u00a0 2016 \u00a0\u00a0 2018 \n Columbia University in the City of New York \n Exchange Program MBA \u00a0 \u00a0\u00a0 2017 \u00a0\u00a0 2017 \n Binghamton University \n Bachelor 's degree \u00a0 Economics \u00a0\u00a0 2009 \u00a0\u00a0 2013 \n\u00a0  Page 2 of 2",
              "extracted_keywords": [
                            "Contact",
                            "LinkedIn",
                            "Top",
                            "Skills",
                            "Business",
                            "Development",
                            "Business",
                            "Strategy",
                            "Startups",
                            "Languages",
                            "English",
                            "FrenchDavid",
                            "Botbol",
                            "EVP",
                            "Director",
                            "Business",
                            "Development",
                            "Food",
                            "Truck",
                            "Promotions",
                            "United",
                            "States",
                            "Summary",
                            "Entrepreneur",
                            "background",
                            "experiences",
                            "companies",
                            "development",
                            "startups",
                            "problem",
                            "sales",
                            "marketing",
                            "Experience",
                            "Food",
                            "Truck",
                            "Promotions",
                            "Executive",
                            "VP",
                            "Director",
                            "Business",
                            "Development",
                            "June",
                            "Present",
                            "years",
                            "months",
                            "Food",
                            "Truck",
                            "Promotions",
                            "marketing",
                            "agency",
                            "Brand",
                            "Streets",
                            "custom",
                            "vehicles",
                            "experiences",
                            "connections",
                            "brands",
                            "consumers",
                            "Food",
                            "Truck",
                            "Association",
                            "Los",
                            "Angeles",
                            "Executive",
                            "VP",
                            "Director",
                            "Business",
                            "Development",
                            "December",
                            "Present",
                            "year",
                            "months",
                            "Los",
                            "Angeles",
                            "California",
                            "United",
                            "States",
                            "New",
                            "York",
                            "Food",
                            "Truck",
                            "Association",
                            "NYFTA",
                            "Executive",
                            "VP",
                            "Director",
                            "Business",
                            "Development",
                            "Present",
                            "years",
                            "Hola",
                            "Business",
                            "Dev",
                            "Manager",
                            "November",
                            "June",
                            "months",
                            "Tel",
                            "Aviv",
                            "Area",
                            "Israel",
                            "Wisor",
                            "Head",
                            "Business",
                            "Development",
                            "December",
                            "November",
                            "year",
                            "Tel",
                            "Aviv",
                            "Area",
                            "Israel",
                            "Page",
                            "Diaphanum",
                            "LLC",
                            "Managing",
                            "Partner",
                            "January",
                            "October",
                            "months",
                            "BHS",
                            "Partners",
                            "LP",
                            "Founder",
                            "Portfolio",
                            "Manager",
                            "January",
                            "December",
                            "year",
                            "Brahman",
                            "Capital",
                            "Research",
                            "Analyst",
                            "June",
                            "December",
                            "year",
                            "months",
                            "Education",
                            "IDC",
                            "Herzliya",
                            "Global",
                            "MBA",
                            "Business",
                            "Strategy",
                            "Development",
                            "Columbia",
                            "University",
                            "City",
                            "New",
                            "York",
                            "Exchange",
                            "Program",
                            "MBA",
                            "Binghamton",
                            "University",
                            "Bachelor",
                            "degree",
                            "Economics",
                            "Page"
              ],
              "keyterms": [
                            [
                                          "Food Truck Promotions",
                                          0.2393093952510786
                            ],
                            [
                                          "Tel Aviv Area Israel",
                                          0.17431230783903343
                            ],
                            [
                                          "Executive VP Director",
                                          0.13984043942785773
                            ],
                            [
                                          "Business Development",
                                          0.09149614027159406
                            ],
                            [
                                          "Food Truck Association",
                                          0.0547609809605157
                            ],
                            [
                                          "United States",
                                          0.025951896057041374
                            ],
                            [
                                          "Business Strategy",
                                          0.025881841695610967
                            ],
                            [
                                          "year",
                                          0.011284185849910732
                            ],
                            [
                                          "experience",
                                          0.010244842371499287
                            ],
                            [
                                          "month",
                                          0.010065377631245931
                            ],
                            [
                                          "Los Angeles",
                                          0.009946789158565771
                            ],
                            [
                                          "June",
                                          0.007568429404667435
                            ],
                            [
                                          "New York",
                                          0.0074630077585136085
                            ],
                            [
                                          "Present",
                                          0.0067425386656319915
                            ],
                            [
                                          "December",
                                          0.005843942673232089
                            ],
                            [
                                          "marketing",
                                          0.0058166591446979655
                            ],
                            [
                                          "strong",
                                          0.005355322377029197
                            ],
                            [
                                          "Manager",
                                          0.0036846745843865246
                            ],
                            [
                                          "agency",
                                          0.0035344531432245246
                            ],
                            [
                                          "experiential",
                                          0.0035000017854141217
                            ]
              ],
              "name": [],
              "phones": [],
              "pos_frequencies": {
                            "ADJ": 9,
                            "ADP": 18,
                            "ADV": 1,
                            "AUX": 2,
                            "CCONJ": 6,
                            "DET": 4,
                            "NOUN": 33,
                            "NUM": 34,
                            "PART": 1,
                            "PRON": 4,
                            "PROPN": 128,
                            "SPACE": 81,
                            "SYM": 2,
                            "VERB": 8
              },
              "resume_data": "\u00a0 \u00a0\nContact\nwww.linkedin.com/in/david-botbol\n(LinkedIn)\nTop Skills\nBusiness Development\nBusiness Strategy\nStart-ups\nLanguages\nEnglish\nFrenchDavid Botbol\nEVP, Director of Business Development at Food Truck Promotions\nUnited States\nSummary\nEntrepreneur with strong multi-cultural background and experiences.\nFounded several companies and assisted in the development of\nmultiple start-ups. Extremely analytical, creative problem solver, and\nstrong in sales / marketing.\nExperience\nFood Truck Promotions\nExecutive VP, Director Of Business Development\nJune 2020\u00a0-\u00a0Present\u00a0 (3 years 5 months)\nFood Truck Promotions is an experiential marketing agency that will Bring Your\nBrand to the Streets\u2122 with custom branded vehicles. We focus on creating\none-of-a-kind experiences and establishing meaningful connections between\nbrands and their consumers.\nFood Truck Association Los Angeles\nExecutive VP, Director of Business Development\nDecember 2021\u00a0-\u00a0Present\u00a0 (1 year 11 months)\nLos Angeles, California, United States\nNew York Food Truck Association (NYFTA)\nExecutive VP, Director of Business Development \n2018\u00a0-\u00a0Present\u00a0 (5 years)\nHola\nBusiness Dev. Manager\nNovember 2017\u00a0-\u00a0June 2018\u00a0 (8 months)\nTel Aviv Area, Israel\nWisor\nHead Of Business Development\nDecember 2016\u00a0-\u00a0November 2017\u00a0 (1 year)\nTel Aviv Area, Israel\n\u00a0 Page 1 of 2 \u00a0 \u00a0\nDiaphanum LLC\nManaging Partner\nJanuary 2016\u00a0-\u00a0October 2016\u00a0 (10 months)\nBHS Partners LP\nFounder / Portfolio Manager\nJanuary 2015\u00a0-\u00a0December 2015\u00a0 (1 year)\nBrahman Capital\nResearch Analyst\nJune 2013\u00a0-\u00a0December 2014\u00a0 (1 year 7 months)\nEducation\nIDC Herzliya\nGlobal MBA,\u00a0Business Strategy and Development \u00a0\u00b7\u00a0(2016\u00a0-\u00a02018)\nColumbia University in the City of New York\nExchange Program, MBA\u00a0 \u00a0\u00b7\u00a0(2017\u00a0-\u00a02017)\nBinghamton University\nBachelor's degree,\u00a0Economics \u00a0\u00b7\u00a0(2009\u00a0-\u00a02013)\n\u00a0 Page 2 of 2",
              "tri_grams": "[Director of Business, Development at Food, Food Truck Promotions, Entrepreneur with strong, strong multicultural background, background and experiences, Founded several companies, companies and assisted, multiple startups Extremely, startups Extremely analytical, Extremely analytical creative, analytical creative problem, creative problem solver, strong in sales, Food Truck Promotions, Executive VP Director, Director Of Business, Food Truck Promotions, experiential marketing agency, \u2122 with custom, custom branded vehicles, vehicles We focus, focus on creating, experiences and establishing, establishing meaningful connections, Food Truck Association, Truck Association Los, Association Los Angeles, Executive VP Director, Director of Business, Los Angeles California, Angeles California United, California United States, New York Food, York Food Truck, Food Truck Association, Truck Association NYFTA, Executive VP Director, Director of Business, Business Dev Manager, Tel Aviv Area, Aviv Area Israel, Head Of Business, Tel Aviv Area, Aviv Area Israel, BHS Partners LP, Strategy and Development, City of New, Exchange Program MBA, Bachelor's degree]",
              "unique_id": "dde06224-1b61-46a8-8084-bec944ad3d88",
              "years": []
}